[
	{
		"id": "1",
		"name": "Test",
		"url": "https://farm9.staticflickr.com/1569/26447419426_07591691fe_z.jpg"
	},
	{
		"id": "2",
		"name": "Test",
		"url": "https://farm9.staticflickr.com/7561/26908723540_5e99cb8bcf_z.jpg"
	},
	{
		"id": "3",
		"name": "Test",
		"url": "https://farm9.staticflickr.com/5718/29570398080_d757d18eb0_z.jpg"
	},
	{
		"id": "4",
		"name": "Test",
		"url": "https://farm9.staticflickr.com/8700/28116178841_fedd841ee7_z.jpg"
	},
	{
		"id": "5",
		"name": "Test",
		"url": "https://farm9.staticflickr.com/7326/27503104934_1824e74bbd_z.jpg"
	}
]
